{
  "volume": [
    10193.896368980408
  ],
  "volume_endpoints": [
    2551.3799920082092
  ],
  "streamlines_count": [
    2541
  ],
  "avg_length": [
    72.93124389648438
  ],
  "std_length": [
    5.862392425537109
  ],
  "min_length": [
    55.79718017578125
  ],
  "max_length": [
    92.18904113769531
  ],
  "span": [
    30.819795608520508
  ],
  "curl": [
    2.3663766243901256
  ],
  "diameter": [
    13.34038477367947
  ],
  "elongation": [
    5.466952050766741
  ],
  "surface_area": [
    5895.7481875728345
  ],
  "end_surface_area_head": [
    1065.496660404729
  ],
  "end_surface_area_tail": [
    1356.086658696928
  ],
  "radius_head": [
    4.537113550657969
  ],
  "radius_tail": [
    5.957507434548587
  ],
  "irregularity": [
    1.9288882902095776
  ],
  "irregularity_of_end_surface_head": [
    0.06069558154443455
  ],
  "irregularity_of_end_surface_tail": [
    0.08222267755037074
  ],
  "mean_curvature": [
    0.3792998370623223
  ],
  "fractal_dimension": [
    2.3673478527157092
  ]
}