{
  "volume": [
    14233.097039699554
  ],
  "volume_endpoints": [
    2685.051381111145
  ],
  "streamlines_count": [
    3520
  ],
  "avg_length": [
    72.39628601074219
  ],
  "std_length": [
    6.52026891708374
  ],
  "min_length": [
    56.64646911621094
  ],
  "max_length": [
    92.48304748535156
  ],
  "span": [
    29.94598960876465
  ],
  "curl": [
    2.417561982642013
  ],
  "diameter": [
    15.821462307761395
  ],
  "elongation": [
    4.575827733396513
  ],
  "surface_area": [
    7542.424844561961
  ],
  "end_surface_area_head": [
    884.6851059118054
  ],
  "end_surface_area_tail": [
    1588.558657330687
  ],
  "radius_head": [
    4.4438897976875085
  ],
  "radius_tail": [
    6.184917113088201
  ],
  "irregularity": [
    2.096033457344417
  ],
  "irregularity_of_end_surface_head": [
    0.07012739682690289
  ],
  "irregularity_of_end_surface_tail": [
    0.0756509497373389
  ],
  "mean_curvature": [
    0.3786094542762095
  ],
  "fractal_dimension": [
    2.372614568859351
  ]
}