{
  "volume": [
    20149.508957386017
  ],
  "volume_endpoints": [
    3917.15288066864
  ],
  "streamlines_count": [
    3880
  ],
  "avg_length": [
    76.24392700195312
  ],
  "std_length": [
    5.8861470222473145
  ],
  "min_length": [
    59.913307189941406
  ],
  "max_length": [
    95.96128845214844
  ],
  "span": [
    30.563329696655273
  ],
  "curl": [
    2.4946210952367847
  ],
  "diameter": [
    18.34360391546514
  ],
  "elongation": [
    4.156431165506869
  ],
  "surface_area": [
    9699.248387441838
  ],
  "end_surface_area_head": [
    923.4304390174319
  ],
  "end_surface_area_tail": [
    2563.6495404889542
  ],
  "radius_head": [
    4.52381735534768
  ],
  "radius_tail": [
    7.281986332582434
  ],
  "irregularity": [
    2.207487674677661
  ],
  "irregularity_of_end_surface_head": [
    0.06962349354749602
  ],
  "irregularity_of_end_surface_tail": [
    0.06498168016527052
  ],
  "mean_curvature": [
    0.38504267281939075
  ],
  "fractal_dimension": [
    2.457953056254209
  ]
}