{
  "volume": [
    12652.287568569183
  ],
  "volume_endpoints": [
    3777.6696920394897
  ],
  "streamlines_count": [
    3187
  ],
  "avg_length": [
    66.91799926757812
  ],
  "std_length": [
    6.075076580047607
  ],
  "min_length": [
    48.56305694580078
  ],
  "max_length": [
    85.60884857177734
  ],
  "span": [
    29.366361618041992
  ],
  "curl": [
    2.27872966143907
  ],
  "diameter": [
    15.51558348700024
  ],
  "elongation": [
    4.312954090553249
  ],
  "surface_area": [
    7142.056402470487
  ],
  "end_surface_area_head": [
    1220.477992827235
  ],
  "end_surface_area_tail": [
    2660.5128732530206
  ],
  "radius_head": [
    5.265095895882608
  ],
  "radius_tail": [
    7.170676800765108
  ],
  "irregularity": [
    2.189587688804149
  ],
  "irregularity_of_end_surface_head": [
    0.07135632767280171
  ],
  "irregularity_of_end_surface_tail": [
    0.06071623099571973
  ],
  "mean_curvature": [
    0.38312975879481564
  ],
  "fractal_dimension": [
    2.3534751238005915
  ]
}