{
  "volume": [
    10472.862746238708
  ],
  "volume_endpoints": [
    2330.5316100120544
  ],
  "streamlines_count": [
    2657
  ],
  "avg_length": [
    73.09943389892578
  ],
  "std_length": [
    4.787104606628418
  ],
  "min_length": [
    60.4862060546875
  ],
  "max_length": [
    89.43480682373047
  ],
  "span": [
    33.29920959472656
  ],
  "curl": [
    2.195230300916878
  ],
  "diameter": [
    13.506124800344196
  ],
  "elongation": [
    5.412317373008643
  ],
  "surface_area": [
    6083.017297583363
  ],
  "end_surface_area_head": [
    904.0577724646187
  ],
  "end_surface_area_tail": [
    1369.0017697321368
  ],
  "radius_head": [
    4.408546513947332
  ],
  "radius_tail": [
    6.125869006063243
  ],
  "irregularity": [
    1.9612113892478957
  ],
  "irregularity_of_end_surface_head": [
    0.06753743196507783
  ],
  "irregularity_of_end_surface_tail": [
    0.08611548950946549
  ],
  "mean_curvature": [
    0.3730736946673783
  ],
  "fractal_dimension": [
    2.3343394001869457
  ]
}