{
  "volume": [
    3614.939305305481
  ],
  "volume_endpoints": [
    1778.4106550216675
  ],
  "streamlines_count": [
    3313
  ],
  "avg_length": [
    25.05816650390625
  ],
  "std_length": [
    3.8361051082611084
  ],
  "min_length": [
    20.08732795715332
  ],
  "max_length": [
    37.40461349487305
  ],
  "span": [
    11.92672061920166
  ],
  "curl": [
    2.101010605007663
  ],
  "diameter": [
    13.55285896437049
  ],
  "elongation": [
    1.8489210704385253
  ],
  "surface_area": [
    2524.904207383328
  ],
  "end_surface_area_head": [
    1091.3268824751467
  ],
  "end_surface_area_tail": [
    471.4015527851226
  ],
  "radius_head": [
    4.931678622556385
  ],
  "radius_tail": [
    3.1007714842838006
  ],
  "irregularity": [
    2.366545309003477
  ],
  "irregularity_of_end_surface_head": [
    0.07001394591452655
  ],
  "irregularity_of_end_surface_tail": [
    0.0640764417647697
  ],
  "mean_curvature": [
    0.4068476137278701
  ],
  "fractal_dimension": [
    2.3259308260301435
  ]
}