{
  "volume": [
    12361.697592258453
  ],
  "volume_endpoints": [
    2098.0596289634705
  ],
  "streamlines_count": [
    2243
  ],
  "avg_length": [
    76.87483215332031
  ],
  "std_length": [
    4.773443698883057
  ],
  "min_length": [
    62.206581115722656
  ],
  "max_length": [
    91.89869689941406
  ],
  "span": [
    32.84723663330078
  ],
  "curl": [
    2.3403744129691573
  ],
  "diameter": [
    14.308760897899765
  ],
  "elongation": [
    5.372570881703948
  ],
  "surface_area": [
    6528.588628298067
  ],
  "end_surface_area_head": [
    1013.8362162638938
  ],
  "end_surface_area_tail": [
    968.6333276406629
  ],
  "radius_head": [
    4.590741928338568
  ],
  "radius_tail": [
    4.788891703576953
  ],
  "irregularity": [
    1.889223000843478
  ],
  "irregularity_of_end_surface_head": [
    0.06530520998603571
  ],
  "irregularity_of_end_surface_tail": [
    0.07438074037910171
  ],
  "mean_curvature": [
    0.3762655189751622
  ],
  "fractal_dimension": [
    2.370425397374174
  ]
}