{
  "volume": [
    14244.720638751984
  ],
  "volume_endpoints": [
    3795.1050906181335
  ],
  "streamlines_count": [
    3408
  ],
  "avg_length": [
    74.01263427734375
  ],
  "std_length": [
    5.69527530670166
  ],
  "min_length": [
    58.39699172973633
  ],
  "max_length": [
    91.69315338134766
  ],
  "span": [
    30.921186447143555
  ],
  "curl": [
    2.3935897286431875
  ],
  "diameter": [
    15.654135783049863
  ],
  "elongation": [
    4.7279923531443915
  ],
  "surface_area": [
    7904.047953547809
  ],
  "end_surface_area_head": [
    942.8031055702452
  ],
  "end_surface_area_tail": [
    2763.8337615346913
  ],
  "radius_head": [
    4.533660166018807
  ],
  "radius_tail": [
    7.542316616987423
  ],
  "irregularity": [
    2.1715245078933187
  ],
  "irregularity_of_end_surface_head": [
    0.06848994140134082
  ],
  "irregularity_of_end_surface_tail": [
    0.06466175299146991
  ],
  "mean_curvature": [
    0.3812765257669167
  ],
  "fractal_dimension": [
    2.3917470938726155
  ]
}