{
  "volume": [
    9513.9158244133
  ],
  "volume_endpoints": [
    2632.7451853752136
  ],
  "streamlines_count": [
    2329
  ],
  "avg_length": [
    61.33128356933594
  ],
  "std_length": [
    4.806204795837402
  ],
  "min_length": [
    47.08205032348633
  ],
  "max_length": [
    76.4544906616211
  ],
  "span": [
    27.391626358032227
  ],
  "curl": [
    2.239052284361763
  ],
  "diameter": [
    14.053797278251379
  ],
  "elongation": [
    4.364036449013514
  ],
  "surface_area": [
    5837.630187914395
  ],
  "end_surface_area_head": [
    845.9397728061789
  ],
  "end_surface_area_tail": [
    1950.1817663165345
  ],
  "radius_head": [
    4.165364298241905
  ],
  "radius_tail": [
    7.070477100104335
  ],
  "irregularity": [
    2.1558124110113375
  ],
  "irregularity_of_end_surface_head": [
    0.06443419529387372
  ],
  "irregularity_of_end_surface_tail": [
    0.08053269282704259
  ],
  "mean_curvature": [
    0.3960991537125646
  ],
  "fractal_dimension": [
    2.3159864169392854
  ]
}