{
  "volume": [
    28890.455444812775
  ],
  "volume_endpoints": [
    8165.578334331512
  ],
  "streamlines_count": [
    8850
  ],
  "avg_length": [
    62.61110305786133
  ],
  "std_length": [
    9.870394706726074
  ],
  "min_length": [
    31.973716735839844
  ],
  "max_length": [
    96.58736419677734
  ],
  "span": [
    29.260095596313477
  ],
  "curl": [
    2.1398119788012515
  ],
  "diameter": [
    24.238546655287905
  ],
  "elongation": [
    2.5831211725807837
  ],
  "surface_area": [
    14955.698578771835
  ],
  "end_surface_area_head": [
    1595.0162128482916
  ],
  "end_surface_area_tail": [
    7690.948621466863
  ],
  "radius_head": [
    5.870823628901122
  ],
  "radius_tail": [
    13.784745856887284
  ],
  "irregularity": [
    3.136887184562117
  ],
  "irregularity_of_end_surface_head": [
    0.06788640923569816
  ],
  "irregularity_of_end_surface_tail": [
    0.07761890109476903
  ],
  "mean_curvature": [
    0.3665469105230213
  ],
  "fractal_dimension": [
    2.4162700253563933
  ]
}