{
  "volume": [
    5782.740528583527
  ],
  "volume_endpoints": [
    616.0507497787476
  ],
  "streamlines_count": [
    122
  ],
  "avg_length": [
    75.0074691772461
  ],
  "std_length": [
    12.609429359436035
  ],
  "min_length": [
    43.36338424682617
  ],
  "max_length": [
    104.60424041748047
  ],
  "span": [
    19.569013595581055
  ],
  "curl": [
    3.8329713866714155
  ],
  "diameter": [
    9.907627186806753
  ],
  "elongation": [
    7.570679413243156
  ],
  "surface_area": [
    5547.040189622196
  ],
  "end_surface_area_head": [
    684.5008848660684
  ],
  "end_surface_area_tail": [
    607.0102186548154
  ],
  "radius_head": [
    3.870972704322639
  ],
  "radius_tail": [
    5.895933453223545
  ],
  "irregularity": [
    2.3759498596451993
  ],
  "irregularity_of_end_surface_head": [
    0.06877270027580196
  ],
  "irregularity_of_end_surface_tail": [
    0.17991153814564728
  ],
  "mean_curvature": [
    0.3755513444298603
  ],
  "fractal_dimension": [
    2.0112494516204293
  ]
}