{
  "volume": [
    11658.469849586487
  ],
  "volume_endpoints": [
    924.0761246681213
  ],
  "streamlines_count": [
    259
  ],
  "avg_length": [
    80.27275848388672
  ],
  "std_length": [
    11.260211944580078
  ],
  "min_length": [
    55.513248443603516
  ],
  "max_length": [
    108.5553207397461
  ],
  "span": [
    28.33732795715332
  ],
  "curl": [
    2.8327568006856874
  ],
  "diameter": [
    13.598523077505
  ],
  "elongation": [
    5.903049766976226
  ],
  "surface_area": [
    7710.321288019676
  ],
  "end_surface_area_head": [
    548.8922189963756
  ],
  "end_surface_area_tail": [
    723.2462179716949
  ],
  "radius_head": [
    3.7350892794740966
  ],
  "radius_tail": [
    4.09373415929507
  ],
  "irregularity": [
    2.2483435502865867
  ],
  "irregularity_of_end_surface_head": [
    0.07984813423801239
  ],
  "irregularity_of_end_surface_tail": [
    0.07279523880396767
  ],
  "mean_curvature": [
    0.39588750455830546
  ],
  "fractal_dimension": [
    2.2887231997809616
  ]
}