{
  "volume": [
    10252.014364242554
  ],
  "volume_endpoints": [
    2237.542817592621
  ],
  "streamlines_count": [
    2573
  ],
  "avg_length": [
    75.43904113769531
  ],
  "std_length": [
    5.995809555053711
  ],
  "min_length": [
    56.02109909057617
  ],
  "max_length": [
    94.5
  ],
  "span": [
    29.455936431884766
  ],
  "curl": [
    2.5610810680605574
  ],
  "diameter": [
    13.154113428290682
  ],
  "elongation": [
    5.735015251993176
  ],
  "surface_area": [
    6166.96551931222
  ],
  "end_surface_area_head": [
    1000.921105228685
  ],
  "end_surface_area_tail": [
    1265.6808814504661
  ],
  "radius_head": [
    4.463063074593902
  ],
  "radius_tail": [
    5.6399142927947645
  ],
  "irregularity": [
    1.9781713394864113
  ],
  "irregularity_of_end_surface_head": [
    0.06251958334795328
  ],
  "irregularity_of_end_surface_tail": [
    0.07895336805735977
  ],
  "mean_curvature": [
    0.3759480964521281
  ],
  "fractal_dimension": [
    2.332228775145576
  ]
}