{
  "volume": [
    5277.113969802856
  ],
  "volume_endpoints": [
    1359.9610891342163
  ],
  "streamlines_count": [
    2180
  ],
  "avg_length": [
    77.92825317382812
  ],
  "std_length": [
    3.456019401550293
  ],
  "min_length": [
    69.16889190673828
  ],
  "max_length": [
    89.74500274658203
  ],
  "span": [
    38.986717224121094
  ],
  "curl": [
    1.9988411110852362
  ],
  "diameter": [
    9.28551135766665
  ],
  "elongation": [
    8.39245682570687
  ],
  "surface_area": [
    4016.599531949949
  ],
  "end_surface_area_head": [
    858.8548838413877
  ],
  "end_surface_area_tail": [
    535.9771079611668
  ],
  "radius_head": [
    4.539506253623767
  ],
  "radius_tail": [
    3.4144075906424463
  ],
  "irregularity": [
    1.7668834132889266
  ],
  "irregularity_of_end_surface_head": [
    0.07537847042698793
  ],
  "irregularity_of_end_surface_tail": [
    0.0683336089719982
  ],
  "mean_curvature": [
    0.3191251878002915
  ],
  "fractal_dimension": [
    2.1815982735755983
  ]
}