{
  "volume": [
    2708.2985792160034
  ],
  "volume_endpoints": [
    662.5451459884644
  ],
  "streamlines_count": [
    151
  ],
  "avg_length": [
    61.02094268798828
  ],
  "std_length": [
    5.221286773681641
  ],
  "min_length": [
    47.73551940917969
  ],
  "max_length": [
    76.86994934082031
  ],
  "span": [
    19.626798629760742
  ],
  "curl": [
    3.109062452776189
  ],
  "diameter": [
    7.517334472719316
  ],
  "elongation": [
    8.117364327666346
  ],
  "surface_area": [
    2621.7675401473944
  ],
  "end_surface_area_head": [
    929.8879945350363
  ],
  "end_surface_area_tail": [
    238.9295541513635
  ],
  "radius_head": [
    4.219107422465378
  ],
  "radius_tail": [
    2.614768510370876
  ],
  "irregularity": [
    1.8192882849268224
  ],
  "irregularity_of_end_surface_head": [
    0.06013958101720177
  ],
  "irregularity_of_end_surface_tail": [
    0.089897267715732
  ],
  "mean_curvature": [
    0.37473491209232257
  ],
  "fractal_dimension": [
    1.8666507261370306
  ]
}