{
  "volume": [
    13942.507063388824
  ],
  "volume_endpoints": [
    2690.8631806373596
  ],
  "streamlines_count": [
    3435
  ],
  "avg_length": [
    75.15972900390625
  ],
  "std_length": [
    6.48068380355835
  ],
  "min_length": [
    58.414451599121094
  ],
  "max_length": [
    95.42253112792969
  ],
  "span": [
    31.796934127807617
  ],
  "curl": [
    2.3637413815370407
  ],
  "diameter": [
    15.368549955722573
  ],
  "elongation": [
    4.890489292772873
  ],
  "surface_area": [
    7535.967289044357
  ],
  "end_surface_area_head": [
    1110.69954902796
  ],
  "end_surface_area_tail": [
    1452.9499914609942
  ],
  "radius_head": [
    4.906811199669632
  ],
  "radius_tail": [
    7.022925124366765
  ],
  "irregularity": [
    2.076686947688361
  ],
  "irregularity_of_end_surface_head": [
    0.06810076223629773
  ],
  "irregularity_of_end_surface_tail": [
    0.10664371910130527
  ],
  "mean_curvature": [
    0.36460548447556196
  ],
  "fractal_dimension": [
    2.400593705949246
  ]
}