{
  "volume": [
    10199.708168506622
  ],
  "volume_endpoints": [
    2138.7422256469727
  ],
  "streamlines_count": [
    1987
  ],
  "avg_length": [
    73.36495208740234
  ],
  "std_length": [
    4.402914047241211
  ],
  "min_length": [
    60.316497802734375
  ],
  "max_length": [
    86.4296875
  ],
  "span": [
    34.205787658691406
  ],
  "curl": [
    2.144811071724025
  ],
  "diameter": [
    13.304685505155616
  ],
  "elongation": [
    5.514219186840091
  ],
  "surface_area": [
    6166.96551931222
  ],
  "end_surface_area_head": [
    988.0059941934761
  ],
  "end_surface_area_tail": [
    1252.7657704152573
  ],
  "radius_head": [
    4.402001987088115
  ],
  "radius_tail": [
    5.511345437960451
  ],
  "irregularity": [
    2.011075596479565
  ],
  "irregularity_of_end_surface_head": [
    0.06161561133069649
  ],
  "irregularity_of_end_surface_tail": [
    0.07617198250239446
  ],
  "mean_curvature": [
    0.38521962185030795
  ],
  "fractal_dimension": [
    2.342622989398191
  ]
}