{
  "volume": [
    11030.79550075531
  ],
  "volume_endpoints": [
    2307.284411907196
  ],
  "streamlines_count": [
    3520
  ],
  "avg_length": [
    63.49128341674805
  ],
  "std_length": [
    4.257857322692871
  ],
  "min_length": [
    50.44963455200195
  ],
  "max_length": [
    77.40404510498047
  ],
  "span": [
    28.233158111572266
  ],
  "curl": [
    2.248819744707345
  ],
  "diameter": [
    14.873097431877243
  ],
  "elongation": [
    4.268867578361204
  ],
  "surface_area": [
    5844.087743431999
  ],
  "end_surface_area_head": [
    968.6333276406629
  ],
  "end_surface_area_tail": [
    1343.1715476617192
  ],
  "radius_head": [
    4.426999163024605
  ],
  "radius_tail": [
    6.3858832646978705
  ],
  "irregularity": [
    1.9699324133638432
  ],
  "irregularity_of_end_surface_head": [
    0.06356372568553066
  ],
  "irregularity_of_end_surface_tail": [
    0.09538066360105739
  ],
  "mean_curvature": [
    0.37058158048682593
  ],
  "fractal_dimension": [
    2.3554256924150945
  ]
}