{
  "volume": [
    13686.787884235382
  ],
  "volume_endpoints": [
    3388.2791237831116
  ],
  "streamlines_count": [
    2802
  ],
  "avg_length": [
    69.4941635131836
  ],
  "std_length": [
    8.704263687133789
  ],
  "min_length": [
    50.67698669433594
  ],
  "max_length": [
    95.08617401123047
  ],
  "span": [
    30.729679107666016
  ],
  "curl": [
    2.26146726979154
  ],
  "diameter": [
    15.835495666656662
  ],
  "elongation": [
    4.388505732694621
  ],
  "surface_area": [
    7297.037734892993
  ],
  "end_surface_area_head": [
    1188.190215239213
  ],
  "end_surface_area_tail": [
    2311.8048753023822
  ],
  "radius_head": [
    4.75977295639785
  ],
  "radius_tail": [
    7.141339391768088
  ],
  "irregularity": [
    2.1106524483261455
  ],
  "irregularity_of_end_surface_head": [
    0.05990131760523939
  ],
  "irregularity_of_end_surface_tail": [
    0.0693039589576925
  ],
  "mean_curvature": [
    0.3842904991034862
  ],
  "fractal_dimension": [
    2.3693464944438114
  ]
}