{
  "volume": [
    2748.9811758995056
  ],
  "volume_endpoints": [
    895.0171270370483
  ],
  "streamlines_count": [
    1034
  ],
  "avg_length": [
    54.544795989990234
  ],
  "std_length": [
    4.759422779083252
  ],
  "min_length": [
    42.155059814453125
  ],
  "max_length": [
    70.13832092285156
  ],
  "span": [
    27.19416046142578
  ],
  "curl": [
    2.0057539951402665
  ],
  "diameter": [
    8.01058589207541
  ],
  "elongation": [
    6.809089462975421
  ],
  "surface_area": [
    2369.922874960822
  ],
  "end_surface_area_head": [
    761.9915510773214
  ],
  "end_surface_area_tail": [
    232.47199863375909
  ],
  "radius_head": [
    4.145798333858881
  ],
  "radius_tail": [
    2.34752821264801
  ],
  "irregularity": [
    1.7265006135642205
  ],
  "irregularity_of_end_surface_head": [
    0.07086243344415225
  ],
  "irregularity_of_end_surface_tail": [
    0.0744733455437825
  ],
  "mean_curvature": [
    0.335511493483987
  ],
  "fractal_dimension": [
    2.0261536974788426
  ]
}