{
  "volume": [
    15354.774348258972
  ],
  "volume_endpoints": [
    3603.3157062530518
  ],
  "streamlines_count": [
    3022
  ],
  "avg_length": [
    83.17950439453125
  ],
  "std_length": [
    6.088039875030518
  ],
  "min_length": [
    66.37945556640625
  ],
  "max_length": [
    102.93660736083984
  ],
  "span": [
    36.61643600463867
  ],
  "curl": [
    2.2716439247116744
  ],
  "diameter": [
    15.330934012913655
  ],
  "elongation": [
    5.425599270368455
  ],
  "surface_area": [
    8523.973283237832
  ],
  "end_surface_area_head": [
    955.718216605454
  ],
  "end_surface_area_tail": [
    2621.7675401473944
  ],
  "radius_head": [
    4.776302573302669
  ],
  "radius_tail": [
    8.218946119538158
  ],
  "irregularity": [
    2.1276846694262166
  ],
  "irregularity_of_end_surface_head": [
    0.07499005476708964
  ],
  "irregularity_of_end_surface_tail": [
    0.08094461415999583
  ],
  "mean_curvature": [
    0.37231229662816306
  ],
  "fractal_dimension": [
    2.4100358755024867
  ]
}