{
  "volume": [
    11083.101696491241
  ],
  "volume_endpoints": [
    2743.169376373291
  ],
  "streamlines_count": [
    2407
  ],
  "avg_length": [
    67.16426086425781
  ],
  "std_length": [
    5.956672191619873
  ],
  "min_length": [
    51.39883804321289
  ],
  "max_length": [
    87.1718521118164
  ],
  "span": [
    30.277294158935547
  ],
  "curl": [
    2.2183045985447167
  ],
  "diameter": [
    14.494945893723454
  ],
  "elongation": [
    4.633633085401238
  ],
  "surface_area": [
    6237.998630005869
  ],
  "end_surface_area_head": [
    1046.1239938519159
  ],
  "end_surface_area_tail": [
    1672.5068790595446
  ],
  "radius_head": [
    4.6490639702993946
  ],
  "radius_tail": [
    6.183731852569855
  ],
  "irregularity": [
    2.039579151738761
  ],
  "irregularity_of_end_surface_head": [
    0.0649079291750578
  ],
  "irregularity_of_end_surface_tail": [
    0.07182626073014418
  ],
  "mean_curvature": [
    0.38292418916194726
  ],
  "fractal_dimension": [
    2.3462208906029502
  ]
}