{
  "volume": [
    8159.766534805298
  ],
  "volume_endpoints": [
    2347.9670085906982
  ],
  "streamlines_count": [
    1451
  ],
  "avg_length": [
    77.01405334472656
  ],
  "std_length": [
    7.293290138244629
  ],
  "min_length": [
    54.055416107177734
  ],
  "max_length": [
    97.22322845458984
  ],
  "span": [
    37.36689758300781
  ],
  "curl": [
    2.0610234813753405
  ],
  "diameter": [
    11.61472509521017
  ],
  "elongation": [
    6.630725455265972
  ],
  "surface_area": [
    5495.37974548136
  ],
  "end_surface_area_head": [
    1214.0204373096308
  ],
  "end_surface_area_tail": [
    1310.8837700736972
  ],
  "radius_head": [
    4.936929332122522
  ],
  "radius_tail": [
    5.3617194490105184
  ],
  "irregularity": [
    1.9555499769907025
  ],
  "irregularity_of_end_surface_head": [
    0.06307215882705787
  ],
  "irregularity_of_end_surface_tail": [
    0.06889597616229544
  ],
  "mean_curvature": [
    0.36281309408783335
  ],
  "fractal_dimension": [
    2.2711633517960026
  ]
}