{
  "volume": [
    5434.032557010651
  ],
  "volume_endpoints": [
    1301.8430938720703
  ],
  "streamlines_count": [
    2522
  ],
  "avg_length": [
    55.78181838989258
  ],
  "std_length": [
    4.7685041427612305
  ],
  "min_length": [
    40.67333221435547
  ],
  "max_length": [
    69.34859466552734
  ],
  "span": [
    25.47332763671875
  ],
  "curl": [
    2.1898127792886153
  ],
  "diameter": [
    11.137041645691026
  ],
  "elongation": [
    5.008674670034553
  ],
  "surface_area": [
    3583.9433122704527
  ],
  "end_surface_area_head": [
    710.3311069364861
  ],
  "end_surface_area_tail": [
    542.4346634787712
  ],
  "radius_head": [
    3.9126936209327496
  ],
  "radius_tail": [
    3.5593070214480784
  ],
  "irregularity": [
    1.8363216223767669
  ],
  "irregularity_of_end_surface_head": [
    0.06770811505075398
  ],
  "irregularity_of_end_surface_tail": [
    0.07337250401161453
  ],
  "mean_curvature": [
    0.3730336080270566
  ],
  "fractal_dimension": [
    2.2617109217975297
  ]
}