{
  "volume": [
    11019.17190170288
  ],
  "volume_endpoints": [
    2638.556984901428
  ],
  "streamlines_count": [
    2657
  ],
  "avg_length": [
    69.50115203857422
  ],
  "std_length": [
    5.121757507324219
  ],
  "min_length": [
    56.30215072631836
  ],
  "max_length": [
    85.98587799072266
  ],
  "span": [
    30.470226287841797
  ],
  "curl": [
    2.2809529335955903
  ],
  "diameter": [
    14.208019245390128
  ],
  "elongation": [
    4.8916848181441095
  ],
  "surface_area": [
    6702.942627273387
  ],
  "end_surface_area_head": [
    800.736884182948
  ],
  "end_surface_area_tail": [
    1801.657989411633
  ],
  "radius_head": [
    4.228325174752558
  ],
  "radius_tail": [
    7.498130261021329
  ],
  "irregularity": [
    2.1606781956620678
  ],
  "irregularity_of_end_surface_head": [
    0.07014501244921983
  ],
  "irregularity_of_end_surface_tail": [
    0.09803552583877617
  ],
  "mean_curvature": [
    0.3775182887379011
  ],
  "fractal_dimension": [
    2.3548228929568404
  ]
}