{
  "volume": [
    14076.17845249176
  ],
  "volume_endpoints": [
    2597.874388217926
  ],
  "streamlines_count": [
    1882
  ],
  "avg_length": [
    87.61138916015625
  ],
  "std_length": [
    7.395437717437744
  ],
  "min_length": [
    64.32099914550781
  ],
  "max_length": [
    110.28166198730469
  ],
  "span": [
    41.24530792236328
  ],
  "curl": [
    2.12415408135802
  ],
  "diameter": [
    14.302671304640372
  ],
  "elongation": [
    6.125526294639207
  ],
  "surface_area": [
    8511.058172202624
  ],
  "end_surface_area_head": [
    1155.9024376511911
  ],
  "end_surface_area_tail": [
    2027.6724325277876
  ],
  "radius_head": [
    4.935292242831419
  ],
  "radius_tail": [
    6.32998211934312
  ],
  "irregularity": [
    2.1620013539637006
  ],
  "irregularity_of_end_surface_head": [
    0.06619945926661816
  ],
  "irregularity_of_end_surface_tail": [
    0.06208076250361077
  ],
  "mean_curvature": [
    0.38374618687107764
  ],
  "fractal_dimension": [
    2.3309149146883015
  ]
}