{
  "volume": [
    12570.922375202179
  ],
  "volume_endpoints": [
    2667.615982532501
  ],
  "streamlines_count": [
    2446
  ],
  "avg_length": [
    79.74471282958984
  ],
  "std_length": [
    6.675828456878662
  ],
  "min_length": [
    63.786155700683594
  ],
  "max_length": [
    100.41397857666016
  ],
  "span": [
    37.86188888549805
  ],
  "curl": [
    2.106200064945356
  ],
  "diameter": [
    14.167319312208368
  ],
  "elongation": [
    5.6287792398997905
  ],
  "surface_area": [
    7277.66506834018
  ],
  "end_surface_area_head": [
    1207.5628817920265
  ],
  "end_surface_area_tail": [
    1485.2377690490164
  ],
  "radius_head": [
    5.1346230783049975
  ],
  "radius_tail": [
    5.378578297600761
  ],
  "irregularity": [
    2.050466182852828
  ],
  "irregularity_of_end_surface_head": [
    0.06858943959178262
  ],
  "irregularity_of_end_surface_tail": [
    0.06119118707913916
  ],
  "mean_curvature": [
    0.3761565590601716
  ],
  "fractal_dimension": [
    2.367066178400645
  ]
}