{
  "volume": [
    7869.176558494568
  ],
  "volume_endpoints": [
    1877.2112469673157
  ],
  "streamlines_count": [
    2882
  ],
  "avg_length": [
    69.23111724853516
  ],
  "std_length": [
    4.5224409103393555
  ],
  "min_length": [
    56.92717361450195
  ],
  "max_length": [
    83.35247802734375
  ],
  "span": [
    30.243759155273438
  ],
  "curl": [
    2.289104237773422
  ],
  "diameter": [
    12.030094363861423
  ],
  "elongation": [
    5.754827448112662
  ],
  "surface_area": [
    4746.303305439248
  ],
  "end_surface_area_head": [
    871.7699948765966
  ],
  "end_surface_area_tail": [
    923.4304390174319
  ],
  "radius_head": [
    4.400735751285979
  ],
  "radius_tail": [
    4.380078193603337
  ],
  "irregularity": [
    1.8139914710105611
  ],
  "irregularity_of_end_surface_head": [
    0.06979085816562908
  ],
  "irregularity_of_end_surface_tail": [
    0.06526936896549386
  ],
  "mean_curvature": [
    0.3588535197901279
  ],
  "fractal_dimension": [
    2.340495173636511
  ]
}