{
  "volume": [
    13657.728886604309
  ],
  "volume_endpoints": [
    2597.874388217926
  ],
  "streamlines_count": [
    1773
  ],
  "avg_length": [
    77.78410339355469
  ],
  "std_length": [
    17.054880142211914
  ],
  "min_length": [
    38.99443435668945
  ],
  "max_length": [
    118.30528259277344
  ],
  "span": [
    32.718040466308594
  ],
  "curl": [
    2.377407151679908
  ],
  "diameter": [
    14.951985873272653
  ],
  "elongation": [
    5.202259021164357
  ],
  "surface_area": [
    7774.89684319572
  ],
  "end_surface_area_head": [
    1246.3082148976528
  ],
  "end_surface_area_tail": [
    1343.1715476617192
  ],
  "radius_head": [
    5.114922428370563
  ],
  "radius_tail": [
    8.685730486658935
  ],
  "irregularity": [
    2.127918717870332
  ],
  "irregularity_of_end_surface_head": [
    0.06594813502421853
  ],
  "irregularity_of_end_surface_tail": [
    0.1764538293568547
  ],
  "mean_curvature": [
    0.3926717814118998
  ],
  "fractal_dimension": [
    2.379251710999135
  ]
}