{
  "volume": [
    18144.43812084198
  ],
  "volume_endpoints": [
    2853.5935673713684
  ],
  "streamlines_count": [
    2423
  ],
  "avg_length": [
    65.43994903564453
  ],
  "std_length": [
    7.441524982452393
  ],
  "min_length": [
    46.84200668334961
  ],
  "max_length": [
    90.80416870117188
  ],
  "span": [
    29.133811950683594
  ],
  "curl": [
    2.2461856054545257
  ],
  "diameter": [
    18.789072623913416
  ],
  "elongation": [
    3.4828727497895318
  ],
  "surface_area": [
    8666.03950462513
  ],
  "end_surface_area_head": [
    1188.190215239213
  ],
  "end_surface_area_tail": [
    1523.983102154643
  ],
  "radius_head": [
    4.904987217913319
  ],
  "radius_tail": [
    7.467396277566233
  ],
  "irregularity": [
    2.2434815083508957
  ],
  "irregularity_of_end_surface_head": [
    0.06361208945521764
  ],
  "irregularity_of_end_surface_tail": [
    0.11494977327183689
  ],
  "mean_curvature": [
    0.39502219732172766
  ],
  "fractal_dimension": [
    2.431952493277117
  ]
}