{
  "volume": [
    7160.137016296387
  ],
  "volume_endpoints": [
    1569.185872077942
  ],
  "streamlines_count": [
    2006
  ],
  "avg_length": [
    60.73260498046875
  ],
  "std_length": [
    4.288722515106201
  ],
  "min_length": [
    47.91770553588867
  ],
  "max_length": [
    74.08966064453125
  ],
  "span": [
    28.95638084411621
  ],
  "curl": [
    2.097382449395754
  ],
  "diameter": [
    12.251937453743517
  ],
  "elongation": [
    4.956979678500743
  ],
  "surface_area": [
    4358.8499743829825
  ],
  "end_surface_area_head": [
    968.6333276406629
  ],
  "end_surface_area_tail": [
    574.7224410667933
  ],
  "radius_head": [
    4.393885273197483
  ],
  "radius_tail": [
    3.8375516522757973
  ],
  "irregularity": [
    1.8646415960631813
  ],
  "irregularity_of_end_surface_head": [
    0.06261637058675532
  ],
  "irregularity_of_end_surface_tail": [
    0.08050079797942276
  ],
  "mean_curvature": [
    0.3848766367046807
  ],
  "fractal_dimension": [
    2.291249273950251
  ]
}