{
  "volume": [
    9589.46921825409
  ],
  "volume_endpoints": [
    2028.3180346488953
  ],
  "streamlines_count": [
    2167
  ],
  "avg_length": [
    81.35807800292969
  ],
  "std_length": [
    4.780786037445068
  ],
  "min_length": [
    64.6556396484375
  ],
  "max_length": [
    96.38519287109375
  ],
  "span": [
    38.2070426940918
  ],
  "curl": [
    2.1294000337668275
  ],
  "diameter": [
    12.2504489224661
  ],
  "elongation": [
    6.6412323758786584
  ],
  "surface_area": [
    5973.238853784088
  ],
  "end_surface_area_head": [
    1084.8693269575424
  ],
  "end_surface_area_tail": [
    994.4635497110805
  ],
  "radius_head": [
    4.669830640949285
  ],
  "radius_tail": [
    5.126156509834161
  ],
  "irregularity": [
    1.9076878973832962
  ],
  "irregularity_of_end_surface_head": [
    0.06315019606217293
  ],
  "irregularity_of_end_surface_tail": [
    0.08301273577753898
  ],
  "mean_curvature": [
    0.35658175410573034
  ],
  "fractal_dimension": [
    2.3174462080700384
  ]
}