{
  "volume": [
    13878.577268600464
  ],
  "volume_endpoints": [
    3213.9251379966736
  ],
  "streamlines_count": [
    3908
  ],
  "avg_length": [
    70.95294952392578
  ],
  "std_length": [
    4.976857662200928
  ],
  "min_length": [
    57.18539047241211
  ],
  "max_length": [
    87.19353485107422
  ],
  "span": [
    29.455358505249023
  ],
  "curl": [
    2.408829942140469
  ],
  "diameter": [
    15.781282937520418
  ],
  "elongation": [
    4.49601910090803
  ],
  "surface_area": [
    7264.749957304972
  ],
  "end_surface_area_head": [
    916.9728834998275
  ],
  "end_surface_area_tail": [
    2021.214877010183
  ],
  "radius_head": [
    4.45925814990486
  ],
  "radius_tail": [
    6.459087612286103
  ],
  "irregularity": [
    2.065180607632455
  ],
  "irregularity_of_end_surface_head": [
    0.06812689711024765
  ],
  "irregularity_of_end_surface_tail": [
    0.06484548418853935
  ],
  "mean_curvature": [
    0.3786156376101221
  ],
  "fractal_dimension": [
    2.4567916150874303
  ]
}