{
  "volume": [
    6084.954103946686
  ],
  "volume_endpoints": [
    1394.831886291504
  ],
  "streamlines_count": [
    1541
  ],
  "avg_length": [
    67.46070098876953
  ],
  "std_length": [
    4.564849376678467
  ],
  "min_length": [
    55.33702850341797
  ],
  "max_length": [
    84.18193817138672
  ],
  "span": [
    30.580564498901367
  ],
  "curl": [
    2.2059992055147677
  ],
  "diameter": [
    10.716631266286747
  ],
  "elongation": [
    6.294954012367012
  ],
  "surface_area": [
    4449.255751629445
  ],
  "end_surface_area_head": [
    826.5671062533656
  ],
  "end_surface_area_tail": [
    761.9915510773214
  ],
  "radius_head": [
    4.087621381700145
  ],
  "radius_tail": [
    4.643689899913454
  ],
  "irregularity": [
    1.958972593921968
  ],
  "irregularity_of_end_surface_head": [
    0.06350575430694047
  ],
  "irregularity_of_end_surface_tail": [
    0.08890499001006125
  ],
  "mean_curvature": [
    0.3479715682213218
  ],
  "fractal_dimension": [
    2.1833324954371003
  ]
}