{
  "volume": [
    19550.893606185913
  ],
  "volume_endpoints": [
    4033.388871192932
  ],
  "streamlines_count": [
    3312
  ],
  "avg_length": [
    87.22575378417969
  ],
  "std_length": [
    7.38352108001709
  ],
  "min_length": [
    65.74783325195312
  ],
  "max_length": [
    111.14178466796875
  ],
  "span": [
    34.351497650146484
  ],
  "curl": [
    2.539212545331564
  ],
  "diameter": [
    16.89335855471155
  ],
  "elongation": [
    5.163316311655059
  ],
  "surface_area": [
    9867.144830899553
  ],
  "end_surface_area_head": [
    1078.411771439938
  ],
  "end_surface_area_tail": [
    2602.394873594581
  ],
  "radius_head": [
    4.836965658405292
  ],
  "radius_tail": [
    7.340731649541857
  ],
  "irregularity": [
    2.1314782190686454
  ],
  "irregularity_of_end_surface_head": [
    0.068157124707025
  ],
  "irregularity_of_end_surface_tail": [
    0.06505120925545052
  ],
  "mean_curvature": [
    0.3766368823710847
  ],
  "fractal_dimension": [
    2.4235496798222766
  ]
}