{
  "volume": [
    6294.178886890411
  ],
  "volume_endpoints": [
    1534.3150749206543
  ],
  "streamlines_count": [
    1658
  ],
  "avg_length": [
    55.83223342895508
  ],
  "std_length": [
    6.4079484939575195
  ],
  "min_length": [
    39.679290771484375
  ],
  "max_length": [
    74.63975524902344
  ],
  "span": [
    26.547752380371094
  ],
  "curl": [
    2.1030870195337656
  ],
  "diameter": [
    11.980697413873198
  ],
  "elongation": [
    4.66018224984995
  ],
  "surface_area": [
    3848.7030884922337
  ],
  "end_surface_area_head": [
    1046.1239938519159
  ],
  "end_surface_area_tail": [
    439.1137751971005
  ],
  "radius_head": [
    4.850035960903236
  ],
  "radius_tail": [
    3.552516118466266
  ],
  "irregularity": [
    1.8314599873822877
  ],
  "irregularity_of_end_surface_head": [
    0.07064096558837822
  ],
  "irregularity_of_end_surface_tail": [
    0.09029109616290382
  ],
  "mean_curvature": [
    0.4016713635553353
  ],
  "fractal_dimension": [
    2.33238616848364
  ]
}